MANIFEST.in
setup.py
roi_ctl/__init__.py
roi_ctl/roi_ctl.cpython-38-x86_64-linux-gnu.so
roi_ctl.egg-info/PKG-INFO
roi_ctl.egg-info/SOURCES.txt
roi_ctl.egg-info/dependency_links.txt
roi_ctl.egg-info/entry_points.txt
roi_ctl.egg-info/requires.txt
roi_ctl.egg-info/top_level.txt
roi_ctl/static/README.md
roi_ctl/static/python-app/.dockerignore
roi_ctl/static/python-app/.gitignore
roi_ctl/static/python-app/Dockerfile
roi_ctl/static/python-app/LICENSE
roi_ctl/static/python-app/README.md
roi_ctl/static/python-app/main.py
roi_ctl/static/python-app/main_test.py
roi_ctl/static/python-app/package.json
roi_ctl/static/python-app/product.json
roi_ctl/static/python-app/requirements.txt
roi_ctl/static/python-app/app/__init__.py
roi_ctl/static/python-app/app/app.py
roi_ctl/static/python-app/app/app_logger.py
roi_ctl/static/python-app/app/app_product.py
roi_ctl/static/python-app/app/app_static.py
roi_ctl/static/python-app/static/README.md
roi_ctl/static/python-app/tests/test_app.py
roi_ctl/static/python-app/tests/utils.py
roi_ctl/static/python-pip/.gitignore
roi_ctl/static/python-pip/LICENSE
roi_ctl/static/python-pip/README.md
roi_ctl/static/python-pip/RELEASE.md
roi_ctl/static/python-pip/main.py
roi_ctl/static/python-pip/package.json
roi_ctl/static/python-pip/requirements.txt
roi_ctl/static/python-pip/python_pip/__init__.py
roi_ctl/static/python-pip/python_pip/app.py
roi_ctl/static/python-pip/python_pip/app_logger.py
roi_ctl/static/python-pip/python_pip/app_static.py
roi_ctl/static/python-pip/static/README.md
roi_ctl/static/python-pip/tests/test_app.py
roi_ctl/static/python-pip/tests/utils.py