Metadata-Version: 1.2
Name: roi-ctl
Version: 1.2.0
Summary: Change Module Infomation
Home-page: UNKNOWN
Author: roictl
Author-email: ops@smartahc.com
License: smartahc
Keywords: roi_ctl
Platform: UNKNOWN
Requires-Python: >=3.8
